{
    "type": "astrocraft:chemical_mixer",
    "inputs" : [
      {
        "type": "astrocraft:stacked_item",
        "tag": "forge:dusts/phosphorus",
        "count": 6
      }
    ],
    "fluid_input1": {
      "type": "astrocraft:fluid",
      "amount": 300,
      "tag": "forge:tetraethyl_orthosilicate"
    },
    "fluid_input2": {
        "type": "astrocraft:fluid",
        "amount": 300,
        "tag": "forge:aluminium_hydroxide"
      },
    "fluid_output": {
      "amount": 700,
      "fluid": "astrocraft:silicoaluminophosphate"
    },
    "time": 400
}